atlas/__init__.py
atlas/conf.py
atlas/settings.py
atlas/app_template/.gitignore
atlas/app_template/.nvmrc
atlas/app_template/README.md
atlas/app_template/manage.py
atlas/app_template/package.json
atlas/app_template/settings.py
atlas/app_template/conf/__init__.py
atlas/app_template/conf/conf.py
atlas/app_template/conf/credentials.yaml.template
atlas/app_template/conf/hooks.py
atlas/app_template/conf/profiles.yaml
atlas/app_template/conf/resource_mapping.yaml
atlas/app_template/conf/swagger.yaml
atlas/app_template/conf/artillery/hooks.js
atlas/app_template/docker/docker-compose.yml
atlas/app_template/docker/grafana/lib/dashboards/atlas.json
atlas/app_template/docker/grafana/provisioning/dashboards/atlas.yaml
atlas/app_template/docker/grafana/provisioning/datasources/atlas.yaml
atlas/examples/petstore/.gitignore
atlas/examples/petstore/.nvmrc
atlas/examples/petstore/README.md
atlas/examples/petstore/manage.py
atlas/examples/petstore/package.json
atlas/examples/petstore/settings.py
atlas/examples/petstore/conf/__init__.py
atlas/examples/petstore/conf/conf.py
atlas/examples/petstore/conf/hooks.py
atlas/examples/petstore/conf/profiles.yaml
atlas/examples/petstore/conf/resource_mapping.yaml
atlas/examples/petstore/conf/swagger.yaml
atlas/examples/petstore/conf/artillery/hooks.js
atlas/examples/petstore/docker/docker-compose.yml
atlas/examples/petstore/docker/grafana/provisioning/dashboards/atlas.yaml
atlas/examples/petstore/docker/grafana/provisioning/datasources/atlas.yaml
atlas/examples/petstore/server/.swagger-codegen-ignore
atlas/examples/petstore/server/README.md
atlas/examples/petstore/server/index.js
atlas/examples/petstore/server/package.json
atlas/examples/petstore/server/api/swagger.yaml
atlas/examples/petstore/server/controllers/Pet.js
atlas/examples/petstore/server/controllers/Store.js
atlas/examples/petstore/server/controllers/User.js
atlas/examples/petstore/server/service/PetService.js
atlas/examples/petstore/server/service/StoreService.js
swagger_atlas-1.1.0.dist-info/LICENSE
swagger_atlas-1.1.0.dist-info/METADATA
swagger_atlas-1.1.0.dist-info/WHEEL
swagger_atlas-1.1.0.dist-info/entry_points.txt
swagger_atlas-1.1.0.dist-info/top_level.txt
swagger_atlas-1.1.0.dist-info/RECORD
