Metadata-Version: 2.1
Name: swagger-atlas
Version: 1.1.0
Summary: Transforms your swagger docs to load testing config and run them
Home-page: https://github.com/swagger-atlas/atlas
Author: JTG
Author-email: atlas@joshtechnologygroup.com
License: UNKNOWN
Platform: UNKNOWN
Classifier: Programming Language :: Python :: 3
Classifier: License :: OSI Approved :: Apache Software License
Requires-Dist: six (==1.11.0)
Requires-Dist: PyYAML (==4.2b1)
Requires-Dist: peewee (==3.6.4)
Requires-Dist: pymysql (==0.9.2)
Requires-Dist: psycopg2 (==2.7.5)
Requires-Dist: requests (==2.20.0)
Requires-Dist: inflection (==0.3.1)
Requires-Dist: pysed (==0.7.8)
Requires-Dist: docker-compose (<2.0,>=1.23)
